nfacct/__init__.py
nfacct/get_args.yml
nfacct/nfacct.py
nfacct-0.6.dist-info/LICENSE
nfacct-0.6.dist-info/METADATA
nfacct-0.6.dist-info/WHEEL
nfacct-0.6.dist-info/entry_points.txt
nfacct-0.6.dist-info/top_level.txt
nfacct-0.6.dist-info/RECORD
