Metadata-Version: 2.1
Name: nfacct
Version: 0.6
Summary: operate with nfacct/iptables
Home-page: https://github.com/fun04wr0ng/nfacct
Author: fun04wr0ng
Author-email: fun04wr0ng@gmail.com
License: GPL v3+
Platform: UNKNOWN
Classifier: Programming Language :: Python :: 3.6
Classifier: License :: OSI Approved :: GNU General Public License v3 or later (GPLv3+)
Classifier: Operating System :: POSIX :: Linux
Requires-Python: >=3.6
Requires-Dist: get-args (>=1.2)
Requires-Dist: coloredlogs
